date_time_range_sequence/__init__.py
date_time_range_sequence/main.py
date_time_range_sequence-0.0.1.dist-info/LICENSE
date_time_range_sequence-0.0.1.dist-info/METADATA
date_time_range_sequence-0.0.1.dist-info/WHEEL
date_time_range_sequence-0.0.1.dist-info/top_level.txt
date_time_range_sequence-0.0.1.dist-info/RECORD
